AUTHORS
LICENSE
README.rst
jwtlib/__init__.py
jwtlib/abstract.py
jwtlib/exc.py
jwtlib/main.py
jwtlib/py.typed
jwtlib/types.py
jwtlib-0.3.7.dist-info/LICENSE
jwtlib-0.3.7.dist-info/WHEEL
jwtlib-0.3.7.dist-info/METADATA
jwtlib-0.3.7.dist-info/RECORD
