Metadata-Version: 2.1
Name: jwtlib
Version: 0.3.7
Summary: A little helper library to streamline working with JWT in python
Home-page: http://novopl.github.com/jwtlib
License: Apache 2.0
Author: Mateusz Klos
Author-email: novopl@gmail.com
Requires-Python: >=3.8.1,<4.0
Classifier: Development Status :: 2 - Pre-Alpha
Classifier: Intended Audience :: Developers
Classifier: License :: OSI Approved :: Apache Software License
Classifier: License :: Other/Proprietary License
Classifier: Programming Language :: Python
Classifier: Programming Language :: Python :: 3
Classifier: Programming Language :: Python :: 3.9
Classifier: Topic :: Utilities
Requires-Dist: pyjwt (>=2.4.0)
Project-URL: Documentation, http://novopl.github.com/jwtlib
Project-URL: Repository, http://github.com/novopl/jwtlib
